findreq/__init__.py
findreq/scan.py
findreq-0.1.8.dist-info/licenses/LICENSE
findreq-0.1.8.dist-info/METADATA
findreq-0.1.8.dist-info/WHEEL
findreq-0.1.8.dist-info/entry_points.txt
findreq-0.1.8.dist-info/top_level.txt
findreq-0.1.8.dist-info/RECORD
